somef/__init__.py
somef/__main__.py
somef/configuration.py
somef/evaluation/create_header_corpus.py
somef/evaluation/header_evaluation_interactive.py
somef/evaluation/output_header_evaluation_summary.py
somef/evaluation/update_evaluation.py
somef/export/__init__.py
somef/export/json_export.py
somef/export/turtle_export.py
somef/extract_ontologies.py
somef/extract_software_type.py
somef/extract_workflows.py
somef/header_analysis.py
somef/mapping/__init__.py
somef/mapping/rml.ttl
somef/mapping/yarrrml.yml
somef/models/citation.p
somef/models/deprecated/citation.sk
somef/models/deprecated/description.sk
somef/models/deprecated/installation.sk
somef/models/deprecated/invocation.sk
somef/models/description.p
somef/models/installation.p
somef/models/invocation.p
somef/parser/__init__.py
somef/parser/authors_parser.py
somef/parser/bower_parser.py
somef/parser/cabal_parser.py
somef/parser/cargo_parser.py
somef/parser/codemeta_parser.py
somef/parser/composer_parser.py
somef/parser/create_excerpts.py
somef/parser/description_parser.py
somef/parser/gemspec_parser.py
somef/parser/mardown_parser.py
somef/parser/package_json_parser.py
somef/parser/pom_xml_parser.py
somef/parser/python_parser.py
somef/process_files.py
somef/process_repository.py
somef/process_results.py
somef/regular_expressions.py
somef/rolf/__init__.py
somef/rolf/models/audio.sav
somef/rolf/models/computer_vision.sav
somef/rolf/models/graphs.sav
somef/rolf/models/natural_language_processing.sav
somef/rolf/models/reinforcement_learning.sav
somef/rolf/models/semantic_web.sav
somef/rolf/models_test/astrophysics.sav
somef/rolf/models_test/rationale.md
somef/rolf/models_test/sequential.sav
somef/rolf/preprocessing.py
somef/somef_cli.py
somef/supervised_classification.py
somef/test/__init__.py
somef/test/test_JSON_export.py
somef/test/test_bower_parser.py
somef/test/test_cabal_parser.py
somef/test/test_cargo_parser.py
somef/test/test_cli.py
somef/test/test_codemeta_export.py
somef/test/test_codemeta_gitlab_export.py
somef-0.9.12.dist-info/METADATA
somef-0.9.12.dist-info/WHEEL
somef-0.9.12.dist-info/entry_points.txt
somef-0.9.12.dist-info/licenses/LICENSE
somef-0.9.12.dist-info/RECORD
