Metadata-Version: 2.4
Name: somef
Version: 0.9.12
Summary: SOftware Metadata Extraction Framework: A tool for automatically extracting relevant software metadata from a source code repository (README, package files, etc).
License-File: LICENSE
Author: Daniel Garijo
Author-email: daniel.garijo@upm.es
Requires-Python: >=3.9,<=3.13
Classifier: License :: OSI Approved :: MIT License
Classifier: Operating System :: OS Independent
Classifier: Programming Language :: Python :: 3
Classifier: Programming Language :: Python :: 3.9
Classifier: Programming Language :: Python :: 3.10
Classifier: Programming Language :: Python :: 3.11
Classifier: Programming Language :: Python :: 3.12
Classifier: Programming Language :: Python :: 3.13
Classifier: Topic :: Software Development :: Libraries :: Python Modules
Requires-Dist: bibtexparser (>=1.4.1,<2.0.0)
Requires-Dist: bs4 (>=0.0.1,<0.0.2)
Requires-Dist: chardet (>=5.2.0,<6.0.0)
Requires-Dist: click (>=8.1.7,<9.0.0)
Requires-Dist: click-option-group (>=0.5.6,<0.6.0)
Requires-Dist: contractions (>=0.1.73,<0.2.0)
Requires-Dist: imbalanced-learn (>=0.11.0,<0.12.0)
Requires-Dist: inflect (>=7.0.0,<8.0.0)
Requires-Dist: lxml (>=5.1.0,<6.0.0)
Requires-Dist: markdown (>=3.5.2,<4.0.0)
Requires-Dist: matplotlib (>=3.8.2,<4.0.0)
Requires-Dist: morph-kgc (>=2.6.4,<3.0.0)
Requires-Dist: nbformat (>=5.9.2,<6.0.0)
Requires-Dist: nltk (>=3.9.0,<4.0.0)
Requires-Dist: numpy (>=1.26.3,<2.0.0)
Requires-Dist: pandas (>=2.1.4,<3.0.0)
Requires-Dist: pytest (>=7.4.4,<8.0.0)
Requires-Dist: pyyaml (>=6.0.2,<7.0.0)
Requires-Dist: rdflib (>=7.0.0,<8.0.0)
Requires-Dist: rdflib-jsonld (>=0.6.2,<0.7.0)
Requires-Dist: requests (>=2.31.0,<3.0.0)
Requires-Dist: scikit-learn (==1.3.2)
Requires-Dist: scipy (>=1.11.4,<2.0.0)
Requires-Dist: textblob (>=0.17.1,<0.18.0)
Requires-Dist: tomli (>=2.0.1,<3.0.0)
Requires-Dist: validators (>=0.22.0,<0.23.0)
Requires-Dist: xgboost (>=2.0.3,<3.0.0)
Project-URL: homepage, https://github.com/KnowledgeCaptureAndDiscovery/somef
